{
  "name": "Groups",
  "plural": "groups",
  "base": "PersistedModel",
  "idInjection": true,
  "options": {
    "validateUpsert": true
  },
  "properties": {
    "name": {
      "type": "string",
      "required": false
    },
    "description": {
      "type": "string",
      "required": false
    },
    "gid": {
      "type": "string",
      "required": false
    },
    "pid": {
      "type": "string",
      "required": false
    }
  },
  "validations": [],
  "relations": {},
  "acls": [],
  "methods": {}
}
